mseedindex-3.0.8.dist-info/RECORD
mseedindex-3.0.8.dist-info/METADATA
mseedindex-3.0.8.dist-info/entry_points.txt
mseedindex-3.0.8.dist-info/WHEEL
mseedindex-3.0.8.dist-info/licenses/LICENSE
mseedindex/__main__.py
mseedindex/mseedindex
