Metadata-Version: 2.3
Name: mseedindex
Version: 3.0.8
Summary: A Python package entry for building the C-based mseedindex program
Project-URL: Homepage, https://github.com/EarthScope/mseedindex
Project-URL: Issues, https://github.com/EarthScope/mseedindex/issues
Author-email: EarthScope Data Services <software@earthscope.org>
License: Apache-2.0
License-File: LICENSE
Keywords: data,miniseed,mseed,seismic,seismology,waveform
Classifier: Development Status :: 5 - Production/Stable
Classifier: Intended Audience :: Science/Research
Classifier: License :: OSI Approved :: Apache Software License
Classifier: Operating System :: MacOS :: MacOS X
Classifier: Operating System :: Microsoft :: Windows
Classifier: Operating System :: POSIX :: Linux
Classifier: Operating System :: POSIX :: Other
Classifier: Programming Language :: Python :: 3
Classifier: Topic :: Scientific/Engineering
Requires-Python: >=3.8
